pifacecam-1.2.2.data/purelib/pifacecam/Camera_error.jpg
pifacecam-1.2.2.data/purelib/pifacecam/No_camera.jpg
pifacecam-1.2.2.data/purelib/pifacecam/__init__.py
pifacecam-1.2.2.data/purelib/pifacecam/ef.dat
pifacecam-1.2.2.data/purelib/pifacecam/mpm.dat
pifacecam-1.2.2.data/purelib/pifacecam/pifacecam.cpython-37m-arm-linux-gnueabihf.so
pifacecam-1.2.2.data/purelib/pifacecam/spm.dat
pifacecam-1.2.2.dist-info/LICENSE
pifacecam-1.2.2.dist-info/METADATA
pifacecam-1.2.2.dist-info/WHEEL
pifacecam-1.2.2.dist-info/top_level.txt
pifacecam-1.2.2.dist-info/RECORD
