Metadata-Version: 2.1
Name: pifacecam
Version: 1.2.2
Summary: Facial Recognition for Raspberry Pi
Home-page: https://github.com/tensorfactory/PiFaceCam
Author: Kwong Cheong, Yee
Author-email: yee.kwong.cheong@gmail.com
License: UNKNOWN
Keywords: facial recognition,raspberry pi
Platform: UNKNOWN
Classifier: Development Status :: 5 - Production/Stable
Classifier: Programming Language :: Python :: 3.7
Classifier: License :: Freeware
Classifier: Natural Language :: English
Classifier: Operating System :: POSIX :: Linux
Requires-Python: >=3.7
License-File: LICENSE
